airbyte_lib/__init__.py
airbyte_lib/_executor.py
airbyte_lib/_factories/__init__.py
airbyte_lib/_factories/cache_factories.py
airbyte_lib/_factories/connector_factories.py
airbyte_lib/_file_writers/__init__.py
airbyte_lib/_file_writers/base.py
airbyte_lib/_file_writers/parquet.py
airbyte_lib/_processors.py
airbyte_lib/_util/__init__.py
airbyte_lib/_util/pip_util.py
airbyte_lib/_util/protocol_util.py
airbyte_lib/_util/text_util.py
airbyte_lib/caches/__init__.py
airbyte_lib/caches/_catalog_manager.py
airbyte_lib/caches/base.py
airbyte_lib/caches/duckdb.py
airbyte_lib/caches/postgres.py
airbyte_lib/caches/snowflake.py
airbyte_lib/config.py
airbyte_lib/datasets/__init__.py
airbyte_lib/datasets/_base.py
airbyte_lib/datasets/_lazy.py
airbyte_lib/datasets/_map.py
airbyte_lib/datasets/_sql.py
airbyte_lib/exceptions.py
airbyte_lib/progress.py
airbyte_lib/py.typed
airbyte_lib/registry.py
airbyte_lib/results.py
airbyte_lib/secrets.py
airbyte_lib/source.py
airbyte_lib/strategies.py
airbyte_lib/telemetry.py
airbyte_lib/types.py
airbyte_lib/validate.py
airbyte_lib/version.py
airbyte_lib-0.1.0.dist-info/METADATA
airbyte_lib-0.1.0.dist-info/WHEEL
airbyte_lib-0.1.0.dist-info/entry_points.txt
airbyte_lib-0.1.0.dist-info/RECORD
