Metadata-Version: 2.1
Name: airbyte-lib
Version: 0.1.0
Summary: AirbyteLib
Author: Airbyte
Author-email: contact@airbyte.io
Requires-Python: >=3.9,<4.0
Classifier: Programming Language :: Python :: 3
Classifier: Programming Language :: Python :: 3.9
Classifier: Programming Language :: Python :: 3.10
Classifier: Programming Language :: Python :: 3.11
Classifier: Programming Language :: Python :: 3.12
Requires-Dist: airbyte-cdk (>=0.58.3,<0.59.0)
Requires-Dist: duckdb-engine (>=0.10.0,<0.11.0)
Requires-Dist: jsonschema (==3.2.0)
Requires-Dist: orjson (>=3.9.10,<4.0.0)
Requires-Dist: overrides (>=7.4.0,<8.0.0)
Requires-Dist: pandas (==2.1.4)
Requires-Dist: pendulum (<=3.0.0)
Requires-Dist: psycopg2-binary (>=2.9.9,<3.0.0)
Requires-Dist: pyarrow (>=14.0.2,<15.0.0)
Requires-Dist: python-ulid (>=2.2.0,<3.0.0)
Requires-Dist: requests (>=2.31.0,<3.0.0)
Requires-Dist: rich (>=13.7.0,<14.0.0)
Requires-Dist: snowflake-connector-python (==3.6.0)
Requires-Dist: snowflake-sqlalchemy (>=1.5.1,<2.0.0)
Requires-Dist: sqlalchemy (==1.4.51)
Requires-Dist: types-pyyaml (>=6.0.12.12,<7.0.0.0)
Requires-Dist: ulid (>=1.1,<2.0)
